{
  "self_node": "node20",
  "bucket_size": 4,
  "hash_bits": 160,
  "saved_at": "2025-10-01T18:22:28Z",
  "buckets": {
    "151": [
      {
        "name": "node88",
        "sha": "0bfdae963645dc4b23f326760423f70d102eb75c",
        "dist": ""
      }
    ],
    "155": [
      {
        "name": "node15",
        "sha": "051b9001d5d1f182ca669af3fc5fb8665292b4f2",
        "dist": ""
      }
    ],
    "156": [
      {
        "name": "node75",
        "sha": "1d813d99f815775a5671356b6a12b8ef9ca99c62",
        "dist": ""
      },
      {
        "name": "node28",
        "sha": "1207716b0643115ee89297bb533427d4deb94690",
        "dist": ""
      },
      {
        "name": "node72",
        "sha": "1d310b103b35834cda05d619fea4b1e148f3aeb4",
        "dist": ""
      },
      {
        "name": "node68",
        "sha": "18be83616833f905eedfcc4c393dc6013059edb0",
        "dist": ""
      }
    ],
    "157": [
      {
        "name": "node37",
        "sha": "378c97edb03cf6d2fb992c4efb1ac740f336ac2c",
        "dist": ""
      }
    ],
    "158": [
      {
        "name": "node51",
        "sha": "5a1420ee2549681a88b4b208f59e35eb09e22fa3",
        "dist": ""
      },
      {
        "name": "node43",
        "sha": "6cb7ecced9bcda19ecde9db3d63bf95f70d72b3f",
        "dist": ""
      },
      {
        "name": "node60",
        "sha": "7b34f1cbef01aa80af4ecae0a95fc23731708989",
        "dist": ""
      },
      {
        "name": "node23",
        "sha": "71034ef805e82ac9508b2b95fdbcb9d159b73026",
        "dist": ""
      }
    ],
    "159": [
      {
        "name": "node82",
        "sha": "f53360e1aa2a053fa5e2d29220dfa76ff851e76b",
        "dist": ""
      },
      {
        "name": "node53",
        "sha": "85a1ec43433f5850c5463df2b815c189b91e44b7",
        "dist": ""
      },
      {
        "name": "node30",
        "sha": "dfaa57648a8beea08520461876334a51dc2da66f",
        "dist": ""
      },
      {
        "name": "node8",
        "sha": "c65b8681a4eec1d41b1ba1b013535f1c96d943ab",
        "dist": ""
      }
    ]
  },
  "non_empty_buckets": 6
}